{
    "horizon": 8,
    "decay_base": 0.9,
    "ft_value": 1.5,
    "ft_value_list": {
        "2": 2,
        "3": 1.6,
        "4": 1.3,
        "5": 1.1
    },
    "bench_weights": {
        "0": 0.03,
        "1": 0.21,
        "2": 0.06,
        "3": 0.002
    },
    "vcap_weight": 0.1,
    "ft_use_penalty": 0.2,
    "itb_value": 0.08,
    "itb_loss_per_transfer": 0,
    "no_future_transfer": false,
    "no_transfer_last_gws": 2,
    "no_transfer_by_position": [],
    "force_ft_state_lb": [],
    "force_ft_state_ub": [],
    "randomized": false,
    "randomization_seed": null,
    "randomization_strength": 1.0,
    "xmin_lb": 300,
    "ev_per_price_cutoff": 30,
    "keep_top_ev_percent": 5,
    "banned": [],
    "banned_next_gw": [],
    "locked": [],
    "locked_next_gw": [],
    "price_changes": [],
    "keep": [],
    "delete_tmp": true,
    "single_solve": true,
    "solver": "highs",
    "secs": 600,
    "gap": 0,
    "num_transfers": null,
    "hit_limit": null,
    "weekly_hit_limit": 0,
    "hit_cost": 4,
    "use_wc": [],
    "use_bb": [],
    "use_fh": [],
    "use_tc": [],
    "chip_limits": {
        "bb": 0,
        "wc": 0,
        "fh": 0,
        "tc": 0
    },
    "no_chip_gws": [],
    "allowed_chip_gws": {
        "bb": [],
        "wc": [],
        "fh": [],
        "tc": []
    },
    "forced_chip_gws": {
        "bb": [],
        "wc": [],
        "fh": [],
        "tc": []
    },
    "future_transfer_limit": null,
    "no_transfer_gws": [],
    "booked_transfers": [],
    "only_booked_transfers": false,
    "no_trs_except_wc": false,
    "preseason": false,
    "no_opposing_play": false,
    "opposing_play_group": "position",
    "opposing_play_penalty": 0.5,
    "pick_prices": {
        "G": "",
        "D": "",
        "M": "",
        "F": ""
    },
    "no_gk_rotation_after": null,
    "max_defenders_per_team": 3,
    "double_defense_pick": false,
    "transfer_itb_buffer": null,
    "num_iterations": 1,
    "iteration_criteria": "this_gw_transfer_in_out",
    "iteration_difference": 1,
    "iteration_target": [],
    "report_decay_base": [
        0.85,
        1.0,
        1.017
    ],
    "datasource": "solio",
    "data_weights": {
        "solio": 1,
        "review": 1
    },
    "export_data": "mixed.csv",
    "team_data": "json",
    "team_id": null,
    "team_json": null,
    "export_image": false,
    "solve_name": "regular",
    "override_next_gw": null,
    "binary_files": {
        "fplreview_binary_1.csv": 0.6,
        "fplreview_binary_2.csv": 0.3,
        "fplreview_binary_3.csv": 0.1
    },
    "generate_binary_files": false,
    "verbose": true,
    "print_result_table": true,
    "print_decay_metrics": false,
    "print_transfer_chip_summary": true,
    "print_squads": true,
    "hide_transfers": false,
    "solutions_file": "",
    "save_squads": true,
    "solutions_file_player_type": "name"
}